spackle/__init__.py
spackle/script.py
spackle-0.0.3.dist-info/LICENSE
spackle-0.0.3.dist-info/METADATA
spackle-0.0.3.dist-info/WHEEL
spackle-0.0.3.dist-info/entry_points.txt
spackle-0.0.3.dist-info/top_level.txt
spackle-0.0.3.dist-info/RECORD
