Metadata-Version: 2.1
Name: spackle
Version: 0.0.3
Summary: Help identify gaps in python code coverage.
Home-page: https://github.com/nicholasserra/spackle/
Author: Nicholas Serra
Author-email: nickserra@gmail.com
License: MIT License
Download-URL: https://github.com/nicholasserra/spackle/zipball/master
Keywords: spackle,coverage,testing
Platform: UNKNOWN
Classifier: Development Status :: 4 - Beta
Classifier: Intended Audience :: Developers
Classifier: License :: OSI Approved :: MIT License
Classifier: Topic :: Software Development :: Libraries :: Python Modules
Classifier: Topic :: Internet
Classifier: Programming Language :: Python
Classifier: Programming Language :: Python :: 2
Classifier: Programming Language :: Python :: 2.7
Classifier: Programming Language :: Python :: 3
Classifier: Programming Language :: Python :: 3.1
Classifier: Programming Language :: Python :: 3.2
Classifier: Programming Language :: Python :: 3.3
Classifier: Programming Language :: Python :: 3.4
Classifier: Programming Language :: Python :: 3.5
Classifier: Programming Language :: Python :: 3.6
Classifier: Programming Language :: Python :: 3.7
Classifier: Programming Language :: Python :: 3.8
Classifier: Programming Language :: Python :: 3.9
Requires-Python: >=2.7, <4
Requires-Dist: setuptools
Requires-Dist: coverage
